aiophoenixdb/__init__.py
aiophoenixdb/connection.py
aiophoenixdb/cursors.py
aiophoenixdb/errors.py
aiophoenixdb/meta.py
aiophoenixdb/types.py
aiophoenixdb/avatica/__init__.py
aiophoenixdb/avatica/client.py
aiophoenixdb/avatica/proto/__init__.py
aiophoenixdb/avatica/proto/common_pb.py
aiophoenixdb/avatica/proto/requests_pb.py
aiophoenixdb/avatica/proto/responses_pb.py
aiophoenixdb-0.0.6.data/data/aiophoenixdb/.DS_Store
aiophoenixdb-0.0.6.data/data/aiophoenixdb/__init__.pyi
aiophoenixdb-0.0.6.data/data/aiophoenixdb/connection.pyi
aiophoenixdb-0.0.6.data/data/aiophoenixdb/cursors.pyi
aiophoenixdb-0.0.6.data/data/aiophoenixdb/errors.pyi
aiophoenixdb-0.0.6.data/data/aiophoenixdb/meta.pyi
aiophoenixdb-0.0.6.data/data/aiophoenixdb/types.pyi
aiophoenixdb-0.0.6.data/data/aiophoenixdb/typeshed.pyi
aiophoenixdb-0.0.6.data/data/aiophoenixdb/avatica/.DS_Store
aiophoenixdb-0.0.6.data/data/aiophoenixdb/avatica/__init__.pyi
aiophoenixdb-0.0.6.data/data/aiophoenixdb/avatica/client.pyi
aiophoenixdb-0.0.6.data/data/aiophoenixdb/avatica/proto/__init__.pyi
aiophoenixdb-0.0.6.data/data/aiophoenixdb/avatica/proto/common_pb.pyi
aiophoenixdb-0.0.6.data/data/aiophoenixdb/avatica/proto/requests_pb.pyi
aiophoenixdb-0.0.6.data/data/aiophoenixdb/avatica/proto/responses_pb.pyi
aiophoenixdb-0.0.6.dist-info/LICENSE
aiophoenixdb-0.0.6.dist-info/METADATA
aiophoenixdb-0.0.6.dist-info/NOTICE
aiophoenixdb-0.0.6.dist-info/WHEEL
aiophoenixdb-0.0.6.dist-info/top_level.txt
aiophoenixdb-0.0.6.dist-info/RECORD
